dslabfinal/trafficlight.v
module traffic_signal_controller(
    input wire clk,              // 1Hz clock
    input wire reset,            // Active high reset
    input wire Emergency_Left,   // Emergency from left side
    input wire Emergency_Right,  // Emergency from right side
    
    // Traffic light outputs
    output reg T1_RED, T1_YELLOW, T1_GREEN,
    output reg T2_RED, T2_YELLOW, T2_GREEN,
    
    // Pedestrian signals and buzzer
    output wire T1_WALK, T2_WALK,
    output wire buzzer_walk1, buzzer_walk2,
    
    // State and counter outputs
    output reg [1:0] T1_STATE, T2_STATE,
    output reg [5:0] T1_counter, T2_counter
);

    // State encoding
    parameter RED = 2'b00;
    parameter GREEN = 2'b01;
    parameter YELLOW = 2'b10;
    
    // FSM state registers
    reg [1:0] T1_state, T1_next_state;
    reg [1:0] T2_state, T2_next_state;
    
    // Saved states for emergency recovery
    reg [1:0] T1_saved_state, T2_saved_state;
    
    // Emergency counters
    reg [3:0] emergency_left_counter;
    reg [3:0] emergency_right_counter;
    
    // Emergency flags
    reg emergency_left_active;
    reg emergency_right_active;
    
    // T1_WALK and T2_WALK signals - HIGH when traffic light is RED, LOW during emergencies
    assign T1_WALK = (T1_state == RED) && !emergency_left_active && !emergency_right_active;
    
    // For T2_WALK, it's inactive only during Emergency
    assign T2_WALK = (T2_state == RED) && !emergency_left_active && !emergency_right_active;
    
    // Split buzzer logic for T1 and T2
    assign buzzer_walk1 = (T1_WALK && T1_state == RED && T1_counter >= 55);
    assign buzzer_walk2 = (T2_WALK && T2_state == RED && T2_counter >= 55);
    
    // State update and counter logic
    always @(posedge clk or posedge reset) begin
        if (reset) begin
            // Initialize everything on reset
            T1_state <= RED;
            T2_state <= RED;
            T1_counter <= 0;
            T2_counter <= 0;
            emergency_left_counter <= 0;
            emergency_right_counter <= 0;
            emergency_left_active <= 0;
            emergency_right_active <= 0;
            T1_saved_state <= RED;
            T2_saved_state <= RED;
        end else begin
            // Handle new emergencies
            if (Emergency_Left && !emergency_left_active && !emergency_right_active) begin
                emergency_left_active <= 1;
                emergency_left_counter <= 0;
                T1_saved_state <= T1_state; // Save only T1's state
            end
            
            if (Emergency_Right && !emergency_right_active) begin
                emergency_right_active <= 1;
                emergency_right_counter <= 0;
                T1_saved_state <= T1_state; // Save both T1 and T2 states
                T2_saved_state <= T2_state;
            end
            
            // Process emergency_left - affects only T1
            if (emergency_left_active) begin
                emergency_left_counter <= emergency_left_counter + 1;
                T1_state <= RED; // Force T1 to RED
                
                if (emergency_left_counter >= 9) begin
                    emergency_left_active <= 0;
                    T1_state <= T1_saved_state; // Restore only T1's state
                    
                end
            end
            
            // Process emergency_right - affects both T1 and T2
            if (emergency_right_active) begin
                emergency_right_counter <= emergency_right_counter + 1;
                T1_state <= RED; // Force T1 to RED
                T2_state <= RED; // Force T2 to RED
                
                if (emergency_right_counter >= 9) begin
                    emergency_right_active <= 0;
                    T1_state <= T1_saved_state;
                    T2_state <= T2_saved_state;
                    
                end
            end
            
            // Normal state update for T1 (when not in emergency_left or emergency_right)
            if (!emergency_left_active && !emergency_right_active) begin
                T1_state <= T1_next_state;
                
                if (T1_state != T1_next_state)
                    T1_counter <= 0; // Reset counter on state change
                else
                    T1_counter <= T1_counter + 1; // Increment counter
            end
            
            // Normal state update for T2 (when not in emergency_right)
            if (!emergency_right_active) begin
                T2_state <= T2_next_state;
                
                if (T2_state != T2_next_state)
                    T2_counter <= 0; // Reset counter on state change
                else
                    T2_counter <= T2_counter + 1; // Increment counter
            end
        end
    end
    
    // T1 Next State Logic with RED=60s, GREEN=30s, YELLOW=5s
    always @(*) begin
        T1_next_state = T1_state;
        
        if (!emergency_left_active && !emergency_right_active) begin
            case (T1_state)
                RED:    if (T1_counter >= 59) T1_next_state = GREEN;
                GREEN:  if (T1_counter >= 29) T1_next_state = YELLOW;
                YELLOW: if (T1_counter >= 4)  T1_next_state = RED;
                default: T1_next_state = RED;
            endcase
        end
    end
    
    // T2 Next State Logic with RED=60s, GREEN=30s, YELLOW=5s
    always @(*) begin
        T2_next_state = T2_state;
        
        if (!emergency_right_active) begin
            case (T2_state)
                RED:    if (T2_counter >= 59) T2_next_state = GREEN;
                GREEN:  if (T2_counter >= 29) T2_next_state = YELLOW;
                YELLOW: if (T2_counter >= 4)  T2_next_state = RED;
                default: T2_next_state = RED;
            endcase
        end
    end
    
    // Output Logic for Traffic Lights and State Output
    always @(*) begin
        // T1 Lights
        case (T1_state)
            RED: begin
                T1_RED = 1; T1_YELLOW = 0; T1_GREEN = 0;
            end
            GREEN: begin
                T1_GREEN = 1; T1_RED = 0; T1_YELLOW = 0;
            end
            YELLOW: begin
                T1_YELLOW = 1; T1_RED = 0; T1_GREEN = 0;
            end
            default: begin
                T1_RED = 1; T1_YELLOW = 0; T1_GREEN = 0;
            end
        endcase
        
        // T2 Lights
        case (T2_state)
            RED: begin
                T2_RED = 1; T2_YELLOW = 0; T2_GREEN = 0;
            end
            GREEN: begin
                T2_GREEN = 1; T2_RED = 0; T2_YELLOW = 0;
            end
            YELLOW: begin
                T2_YELLOW = 1; T2_RED = 0; T2_GREEN = 0;
            end
            default: begin
                T2_RED = 1; T2_YELLOW = 0; T2_GREEN = 0;
            end
        endcase
        
        // Output current states
        T1_STATE = T1_state;
        T2_STATE = T2_state;
    end

endmodule

dslabfinal/trafficlightest.v
`timescale 1s/1ms

module traffic_signal_controller_tb;

  // Inputs
  reg clk;
  reg reset;
  reg Emergency_Left;
  reg Emergency_Right;
  
  // Outputs
  wire T1_RED, T1_YELLOW, T1_GREEN;
  wire T2_RED, T2_YELLOW, T2_GREEN;
  wire T1_WALK, T2_WALK;
  wire buzzer_walk1, buzzer_walk2;
  wire [1:0] T1_STATE, T2_STATE;
  wire [5:0] T1_counter, T2_counter;

  // Instantiate the Unit Under Test (UUT)
  traffic_signal_controller uut (
    .clk(clk),
    .reset(reset),
    .Emergency_Left(Emergency_Left),
    .Emergency_Right(Emergency_Right),
    .T1_RED(T1_RED),
    .T1_YELLOW(T1_YELLOW),
    .T1_GREEN(T1_GREEN),
    .T2_RED(T2_RED),
    .T2_YELLOW(T2_YELLOW),
    .T2_GREEN(T2_GREEN),
    .T1_WALK(T1_WALK),
    .T2_WALK(T2_WALK),
    .buzzer_walk1(buzzer_walk1),
    .buzzer_walk2(buzzer_walk2),
    .T1_STATE(T1_STATE),
    .T2_STATE(T2_STATE),
    .T1_counter(T1_counter),
    .T2_counter(T2_counter)
  );
  
  // Clock generation (1Hz)
  initial begin
    clk = 0;
    forever #0.5 clk = ~clk; // 1 time unit per cycle (1s)
  end
// BEEP display for buzzers
always @(posedge clk) begin
  if (buzzer_walk1) begin
    $display("Time=%0t: BEEP from buzzer_walk1", $time);
  end
  if (buzzer_walk2) begin
    $display("Time=%0t: BEEP from buzzer_walk2", $time);
  end
end

  // VCD Dump for GTKWave
  initial begin
    $dumpfile("traffic2.vcd");
    $dumpvars(0, traffic_signal_controller_tb);
  end

  // Monitor for outputs
  initial begin
    $monitor("Time=%0t | T1_STATE=%0d T2_STATE=%0d | T1: R=%b Y=%b G=%b | T2: R=%b Y=%b G=%b | Walk: T1=%b T2=%b ", 
            $time, T1_STATE, T2_STATE, T1_RED, T1_YELLOW, T1_GREEN, T2_RED, T2_YELLOW, T2_GREEN, 
            T1_WALK, T2_WALK);
  end
  
  // Test cases
  initial begin
    // Initialize inputs
    reset = 1;
    Emergency_Left = 0;
    Emergency_Right = 0;
    
    // Apply reset
    #2 reset = 0;
    
    // Case 1: Normal operation for a few cycles
    $display("=== Case 1: Normal Operation ===");
    #100;
    
    // Case 2: Emergency_Left (should only affect T1)
    $display("=== Case 2: Emergency from Left ===");
    Emergency_Left = 1;
    #2;
    Emergency_Left = 0;
    #20;
    
    // Case 3: Emergency_Right (should affect both T1 and T2)
    $display("=== Case 3: Emergency from Right ===");
    Emergency_Right = 1;
    #2;
    Emergency_Right = 0;
    #20;
    
    // Case 4: Buzzer activation during pedestrian walk
    $display("=== Case 4: Pedestrian Signal with Buzzer ===");
    // Wait until we're in RED state with counter near end
    #80;
    
    $display("=== Simulation Complete ===");
    $finish;
  end

endmodule

dslabfinal/traffic2.vcd
$date
	Thu May 08 07:43:22 2025
$end
$version
	Icarus Verilog
$end
$timescale
	1ms
$end
$scope module traffic_signal_controller_tb $end
$var wire 1 ! buzzer_walk2 $end
$var wire 1 " buzzer_walk1 $end
$var wire 6 # T2_counter [5:0] $end
$var wire 1 $ T2_YELLOW $end
$var wire 1 % T2_WALK $end
$var wire 2 & T2_STATE [1:0] $end
$var wire 1 ' T2_RED $end
$var wire 1 ( T2_GREEN $end
$var wire 6 ) T1_counter [5:0] $end
$var wire 1 * T1_YELLOW $end
$var wire 1 + T1_WALK $end
$var wire 2 , T1_STATE [1:0] $end
$var wire 1 - T1_RED $end
$var wire 1 . T1_GREEN $end
$var reg 1 / Emergency_Left $end
$var reg 1 0 Emergency_Right $end
$var reg 1 1 clk $end
$var reg 1 2 reset $end
$scope module uut $end
$var wire 1 / Emergency_Left $end
$var wire 1 0 Emergency_Right $end
$var wire 1 + T1_WALK $end
$var wire 1 % T2_WALK $end
$var wire 1 " buzzer_walk1 $end
$var wire 1 ! buzzer_walk2 $end
$var wire 1 1 clk $end
$var wire 1 2 reset $end
$var parameter 2 3 GREEN $end
$var parameter 2 4 RED $end
$var parameter 2 5 YELLOW $end
$var reg 1 . T1_GREEN $end
$var reg 1 - T1_RED $end
$var reg 2 6 T1_STATE [1:0] $end
$var reg 1 * T1_YELLOW $end
$var reg 6 7 T1_counter [5:0] $end
$var reg 2 8 T1_next_state [1:0] $end
$var reg 2 9 T1_saved_state [1:0] $end
$var reg 2 : T1_state [1:0] $end
$var reg 1 ( T2_GREEN $end
$var reg 1 ' T2_RED $end
$var reg 2 ; T2_STATE [1:0] $end
$var reg 1 $ T2_YELLOW $end
$var reg 6 < T2_counter [5:0] $end
$var reg 2 = T2_next_state [1:0] $end
$var reg 2 > T2_saved_state [1:0] $end
$var reg 2 ? T2_state [1:0] $end
$var reg 1 @ emergency_left_active $end
$var reg 4 A emergency_left_counter [3:0] $end
$var reg 1 B emergency_right_active $end
$var reg 4 C emergency_right_counter [3:0] $end
$upscope $end
$upscope $end
$enddefinitions $end
$comment Show the parameter values. $end
$dumpall
b10 5
b0 4
b1 3
$end
#0
$dumpvars
b0 C
0B
b0 A
0@
b0 ?
b0 >
b0 =
b0 <
b0 ;
b0 :
b0 9
b0 8
b0 7
b0 6
12
01
00
0/
0.
1-
b0 ,
1+
0*
b0 )
0(
1'
b0 &
1%
0$
b0 #
0"
0!
$end
#500
11
#1000
01
#1500
11
#2000
01
02
#2500
b1 #
b1 <
b1 )
b1 7
11
#3000
01
#3500
b10 #
b10 <
b10 )
b10 7
11
#4000
01
#4500
b11 #
b11 <
b11 )
b11 7
11
#5000
01
#5500
b100 #
b100 <
b100 )
b100 7
11
#6000
01
#6500
b101 #
b101 <
b101 )
b101 7
11
#7000
01
#7500
b110 #
b110 <
b110 )
b110 7
11
#8000
01
#8500
b111 #
b111 <
b111 )
b111 7
11
#9000
01
#9500
b1000 #
b1000 <
b1000 )
b1000 7
11
#10000
01
#10500
b1001 #
b1001 <
b1001 )
b1001 7
11
#11000
01
#11500
b1010 #
b1010 <
b1010 )
b1010 7
11
#12000
01
#12500
b1011 #
b1011 <
b1011 )
b1011 7
11
#13000
01
#13500
b1100 #
b1100 <
b1100 )
b1100 7
11
#14000
01
#14500
b1101 #
b1101 <
b1101 )
b1101 7
11
#15000
01
#15500
b1110 #
b1110 <
b1110 )
b1110 7
11
#16000
01
#16500
b1111 #
b1111 <
b1111 )
b1111 7
11
#17000
01
#17500
b10000 #
b10000 <
b10000 )
b10000 7
11
#18000
01
#18500
b10001 #
b10001 <
b10001 )
b10001 7
11
#19000
01
#19500
b10010 #
b10010 <
b10010 )
b10010 7
11
#20000
01
#20500
b10011 #
b10011 <
b10011 )
b10011 7
11
#21000
01
#21500
b10100 #
b10100 <
b10100 )
b10100 7
11
#22000
01
#22500
b10101 #
b10101 <
b10101 )
b10101 7
11
#23000
01
#23500
b10110 #
b10110 <
b10110 )
b10110 7
11
#24000
01
#24500
b10111 #
b10111 <
b10111 )
b10111 7
11
#25000
01
#25500
b11000 #
b11000 <
b11000 )
b11000 7
11
#26000
01
#26500
b11001 #
b11001 <
b11001 )
b11001 7
11
#27000
01
#27500
b11010 #
b11010 <
b11010 )
b11010 7
11
#28000
01
#28500
b11011 #
b11011 <
b11011 )
b11011 7
11
#29000
01
#29500
b11100 #
b11100 <
b11100 )
b11100 7
11
#30000
01
#30500
b11101 #
b11101 <
b11101 )
b11101 7
11
#31000
01
#31500
b11110 #
b11110 <
b11110 )
b11110 7
11
#32000
01
#32500
b11111 #
b11111 <
b11111 )
b11111 7
11
#33000
01
#33500
b100000 #
b100000 <
b100000 )
b100000 7
11
#34000
01
#34500
b100001 #
b100001 <
b100001 )
b100001 7
11
#35000
01
#35500
b100010 #
b100010 <
b100010 )
b100010 7
11
#36000
01
#36500
b100011 #
b100011 <
b100011 )
b100011 7
11
#37000
01
#37500
b100100 #
b100100 <
b100100 )
b100100 7
11
#38000
01
#38500
b100101 #
b100101 <
b100101 )
b100101 7
11
#39000
01
#39500
b100110 #
b100110 <
b100110 )
b100110 7
11
#40000
01
#40500
b100111 #
b100111 <
b100111 )
b100111 7
11
#41000
01
#41500
b101000 #
b101000 <
b101000 )
b101000 7
11
#42000
01
#42500
b101001 #
b101001 <
b101001 )
b101001 7
11
#43000
01
#43500
b101010 #
b101010 <
b101010 )
b101010 7
11
#44000
01
#44500
b101011 #
b101011 <
b101011 )
b101011 7
11
#45000
01
#45500
b101100 #
b101100 <
b101100 )
b101100 7
11
#46000
01
#46500
b101101 #
b101101 <
b101101 )
b101101 7
11
#47000
01
#47500
b101110 #
b101110 <
b101110 )
b101110 7
11
#48000
01
#48500
b101111 #
b101111 <
b101111 )
b101111 7
11
#49000
01
#49500
b110000 #
b110000 <
b110000 )
b110000 7
11
#50000
01
#50500
b110001 #
b110001 <
b110001 )
b110001 7
11
#51000
01
#51500
b110010 #
b110010 <
b110010 )
b110010 7
11
#52000
01
#52500
b110011 #
b110011 <
b110011 )
b110011 7
11
#53000
01
#53500
b110100 #
b110100 <
b110100 )
b110100 7
11
#54000
01
#54500
b110101 #
b110101 <
b110101 )
b110101 7
11
#55000
01
#55500
b110110 #
b110110 <
b110110 )
b110110 7
11
#56000
01
#56500
1!
1"
b110111 #
b110111 <
b110111 )
b110111 7
11
#57000
01
#57500
b111000 #
b111000 <
b111000 )
b111000 7
11
#58000
01
#58500
b111001 #
b111001 <
b111001 )
b111001 7
11
#59000
01
#59500
b111010 #
b111010 <
b111010 )
b111010 7
11
#60000
01
#60500
b1 =
b1 8
b111011 #
b111011 <
b111011 )
b111011 7
11
#61000
01
#61500
0%
0+
0!
0"
b1 &
b1 ;
b1 ,
b1 6
0'
1(
0-
1.
b0 #
b0 <
b1 ?
b0 )
b0 7
b1 :
11
#62000
01
#62500
b1 #
b1 <
b1 )
b1 7
11
#63000
01
#63500
b10 #
b10 <
b10 )
b10 7
11
#64000
01
#64500
b11 #
b11 <
b11 )
b11 7
11
#65000
01
#65500
b100 #
b100 <
b100 )
b100 7
11
#66000
01
#66500
b101 #
b101 <
b101 )
b101 7
11
#67000
01
#67500
b110 #
b110 <
b110 )
b110 7
11
#68000
01
#68500
b111 #
b111 <
b111 )
b111 7
11
#69000
01
#69500
b1000 #
b1000 <
b1000 )
b1000 7
11
#70000
01
#70500
b1001 #
b1001 <
b1001 )
b1001 7
11
#71000
01
#71500
b1010 #
b1010 <
b1010 )
b1010 7
11
#72000
01
#72500
b1011 #
b1011 <
b1011 )
b1011 7
11
#73000
01
#73500
b1100 #
b1100 <
b1100 )
b1100 7
11
#74000
01
#74500
b1101 #
b1101 <
b1101 )
b1101 7
11
#75000
01
#75500
b1110 #
b1110 <
b1110 )
b1110 7
11
#76000
01
#76500
b1111 #
b1111 <
b1111 )
b1111 7
11
#77000
01
#77500
b10000 #
b10000 <
b10000 )
b10000 7
11
#78000
01
#78500
b10001 #
b10001 <
b10001 )
b10001 7
11
#79000
01
#79500
b10010 #
b10010 <
b10010 )
b10010 7
11
#80000
01
#80500
b10011 #
b10011 <
b10011 )
b10011 7
11
#81000
01
#81500
b10100 #
b10100 <
b10100 )
b10100 7
11
#82000
01
#82500
b10101 #
b10101 <
b10101 )
b10101 7
11
#83000
01
#83500
b10110 #
b10110 <
b10110 )
b10110 7
11
#84000
01
#84500
b10111 #
b10111 <
b10111 )
b10111 7
11
#85000
01
#85500
b11000 #
b11000 <
b11000 )
b11000 7
11
#86000
01
#86500
b11001 #
b11001 <
b11001 )
b11001 7
11
#87000
01
#87500
b11010 #
b11010 <
b11010 )
b11010 7
11
#88000
01
#88500
b11011 #
b11011 <
b11011 )
b11011 7
11
#89000
01
#89500
b11100 #
b11100 <
b11100 )
b11100 7
11
#90000
01
#90500
b10 =
b10 8
b11101 #
b11101 <
b11101 )
b11101 7
11
#91000
01
#91500
b10 &
b10 ;
b10 ,
b10 6
0(
1$
0.
1*
b0 #
b0 <
b10 ?
b0 )
b0 7
b10 :
11
#92000
01
#92500
b1 #
b1 <
b1 )
b1 7
11
#93000
01
#93500
b10 #
b10 <
b10 )
b10 7
11
#94000
01
#94500
b11 #
b11 <
b11 )
b11 7
11
#95000
01
#95500
b0 =
b0 8
b100 #
b100 <
b100 )
b100 7
11
#96000
01
#96500
1%
1+
b0 &
b0 ;
b0 ,
b0 6
0$
1'
0*
1-
b0 #
b0 <
b0 ?
b0 )
b0 7
b0 :
11
#97000
01
#97500
b1 #
b1 <
b1 )
b1 7
11
#98000
01
#98500
b10 #
b10 <
b10 )
b10 7
11
#99000
01
#99500
b11 #
b11 <
b11 )
b11 7
11
#100000
01
#100500
b100 #
b100 <
b100 )
b100 7
11
#101000
01
#101500
b101 #
b101 <
b101 )
b101 7
11
#102000
01
1/
#102500
0+
0%
b110 #
b110 <
b110 )
b110 7
1@
11
#103000
01
#103500
b111 #
b111 <
b1 A
11
#104000
01
0/
#104500
b1000 #
b1000 <
b10 A
11
#105000
01
#105500
b1001 #
b1001 <
b11 A
11
#106000
01
#106500
b1010 #
b1010 <
b100 A
11
#107000
01
#107500
b1011 #
b1011 <
b101 A
11
#108000
01
#108500
b1100 #
b1100 <
b110 A
11
#109000
01
#109500
b1101 #
b1101 <
b111 A
11
#110000
01
#110500
b1110 #
b1110 <
b1000 A
11
#111000
01
#111500
b1111 #
b1111 <
b1001 A
11
#112000
01
#112500
1+
1%
b10000 #
b10000 <
0@
b1010 A
11
#113000
01
#113500
b10001 #
b10001 <
b111 )
b111 7
11
#114000
01
#114500
b10010 #
b10010 <
b1000 )
b1000 7
11
#115000
01
#115500
b10011 #
b10011 <
b1001 )
b1001 7
11
#116000
01
#116500
b10100 #
b10100 <
b1010 )
b1010 7
11
#117000
01
#117500
b10101 #
b10101 <
b1011 )
b1011 7
11
#118000
01
#118500
b10110 #
b10110 <
b1100 )
b1100 7
11
#119000
01
#119500
b10111 #
b10111 <
b1101 )
b1101 7
11
#120000
01
#120500
b11000 #
b11000 <
b1110 )
b1110 7
11
#121000
01
#121500
b11001 #
b11001 <
b1111 )
b1111 7
11
#122000
01
#122500
b11010 #
b11010 <
b10000 )
b10000 7
11
#123000
01
#123500
b11011 #
b11011 <
b10001 )
b10001 7
11
#124000
01
10
#124500
0+
0%
b11100 #
b11100 <
b10010 )
b10010 7
1B
11
#125000
01
#125500
b1 C
11
#126000
01
00
#126500
b10 C
11
#127000
01
#127500
b11 C
11
#128000
01
#128500
b100 C
11
#129000
01
#129500
b101 C
11
#130000
01
#130500
b110 C
11
#131000
01
#131500
b111 C
11
#132000
01
#132500
b1000 C
11
#133000
01
#133500
b1001 C
11
#134000
01
#134500
1+
1%
0B
b1010 C
11
#135000
01
#135500
b11101 #
b11101 <
b10011 )
b10011 7
11
#136000
01
#136500
b11110 #
b11110 <
b10100 )
b10100 7
11
#137000
01
#137500
b11111 #
b11111 <
b10101 )
b10101 7
11
#138000
01
#138500
b100000 #
b100000 <
b10110 )
b10110 7
11
#139000
01
#139500
b100001 #
b100001 <
b10111 )
b10111 7
11
#140000
01
#140500
b100010 #
b100010 <
b11000 )
b11000 7
11
#141000
01
#141500
b100011 #
b100011 <
b11001 )
b11001 7
11
#142000
01
#142500
b100100 #
b100100 <
b11010 )
b11010 7
11
#143000
01
#143500
b100101 #
b100101 <
b11011 )
b11011 7
11
#144000
01
#144500
b100110 #
b100110 <
b11100 )
b11100 7
11
#145000
01
#145500
b100111 #
b100111 <
b11101 )
b11101 7
11
#146000
01
#146500
b101000 #
b101000 <
b11110 )
b11110 7
11
#147000
01
#147500
b101001 #
b101001 <
b11111 )
b11111 7
11
#148000
01
#148500
b101010 #
b101010 <
b100000 )
b100000 7
11
#149000
01
#149500
b101011 #
b101011 <
b100001 )
b100001 7
11
#150000
01
#150500
b101100 #
b101100 <
b100010 )
b100010 7
11
#151000
01
#151500
b101101 #
b101101 <
b100011 )
b100011 7
11
#152000
01
#152500
b101110 #
b101110 <
b100100 )
b100100 7
11
#153000
01
#153500
b101111 #
b101111 <
b100101 )
b100101 7
11
#154000
01
#154500
b110000 #
b110000 <
b100110 )
b100110 7
11
#155000
01
#155500
b110001 #
b110001 <
b100111 )
b100111 7
11
#156000
01
#156500
b110010 #
b110010 <
b101000 )
b101000 7
11
#157000
01
#157500
b110011 #
b110011 <
b101001 )
b101001 7
11
#158000
01
#158500
b110100 #
b110100 <
b101010 )
b101010 7
11
#159000
01
#159500
b110101 #
b110101 <
b101011 )
b101011 7
11
#160000
01
#160500
b110110 #
b110110 <
b101100 )
b101100 7
11
#161000
01
#161500
1!
b110111 #
b110111 <
b101101 )
b101101 7
11
#162000
01
#162500
b111000 #
b111000 <
b101110 )
b101110 7
11
#163000
01
#163500
b111001 #
b111001 <
b101111 )
b101111 7
11
#164000
01
#164500
b111010 #
b111010 <
b110000 )
b110000 7
11
#165000
01
#165500
b1 =
b111011 #
b111011 <
b110001 )
b110001 7
11
#166000
01
#166500
0%
0!
b1 &
b1 ;
0'
1(
b0 #
b0 <
b1 ?
b110010 )
b110010 7
11
#167000
01
#167500
b1 #
b1 <
b110011 )
b110011 7
11
#168000
01
#168500
b10 #
b10 <
b110100 )
b110100 7
11
#169000
01
#169500
b11 #
b11 <
b110101 )
b110101 7
11
#170000
01
#170500
b100 #
b100 <
b110110 )
b110110 7
11
#171000
01
#171500
1"
b101 #
b101 <
b110111 )
b110111 7
11
#172000
01
#172500
b110 #
b110 <
b111000 )
b111000 7
11
#173000
01
#173500
b111 #
b111 <
b111001 )
b111001 7
11
#174000
01
#174500
b1000 #
b1000 <
b111010 )
b111010 7
11
#175000
01
#175500
b1 8
b1001 #
b1001 <
b111011 )
b111011 7
11
#176000
01
#176500
0+
0"
b1 ,
b1 6
0-
1.
b1010 #
b1010 <
b0 )
b0 7
b1 :
11
#177000
01
#177500
b1011 #
b1011 <
b1 )
b1 7
11
#178000
01
#178500
b1100 #
b1100 <
b10 )
b10 7
11
#179000
01
#179500
b1101 #
b1101 <
b11 )
b11 7
11
#180000
01
#180500
b1110 #
b1110 <
b100 )
b100 7
11
#181000
01
#181500
b1111 #
b1111 <
b101 )
b101 7
11
#182000
01
#182500
b10000 #
b10000 <
b110 )
b110 7
11
#183000
01
#183500
b10001 #
b10001 <
b111 )
b111 7
11
#184000
01
#184500
b10010 #
b10010 <
b1000 )
b1000 7
11
#185000
01
#185500
b10011 #
b10011 <
b1001 )
b1001 7
11
#186000
01
#186500
b10100 #
b10100 <
b1010 )
b1010 7
11
#187000
01
#187500
b10101 #
b10101 <
b1011 )
b1011 7
11
#188000
01
#188500
b10110 #
b10110 <
b1100 )
b1100 7
11
#189000
01
#189500
b10111 #
b10111 <
b1101 )
b1101 7
11
#190000
01
#190500
b11000 #
b11000 <
b1110 )
b1110 7
11
#191000
01
#191500
b11001 #
b11001 <
b1111 )
b1111 7
11
#192000
01
#192500
b11010 #
b11010 <
b10000 )
b10000 7
11
#193000
01
#193500
b11011 #
b11011 <
b10001 )
b10001 7
11
#194000
01
#194500
b11100 #
b11100 <
b10010 )
b10010 7
11
#195000
01
#195500
b10 =
b11101 #
b11101 <
b10011 )
b10011 7
11
#196000
01
#196500
b10 &
b10 ;
0(
1$
b0 #
b0 <
b10 ?
b10100 )
b10100 7
11
#197000
01
#197500
b1 #
b1 <
b10101 )
b10101 7
11
#198000
01
#198500
b10 #
b10 <
b10110 )
b10110 7
11
#199000
01
#199500
b11 #
b11 <
b10111 )
b10111 7
11
#200000
01
#200500
b0 =
b100 #
b100 <
b11000 )
b11000 7
11
#201000
01
#201500
1%
b0 &
b0 ;
0$
1'
b0 #
b0 <
b0 ?
b11001 )
b11001 7
11
#202000
01
#202500
b1 #
b1 <
b11010 )
b11010 7
11
#203000
01
#203500
b10 #
b10 <
b11011 )
b11011 7
11
#204000
01
#204500
b11 #
b11 <
b11100 )
b11100 7
11
#205000
01
#205500
b10 8
b100 #
b100 <
b11101 )
b11101 7
11
#206000
01
#206500
b10 ,
b10 6
0.
1*
b101 #
b101 <
b0 )
b0 7
b10 :
11
#207000
01
#207500
b110 #
b110 <
b1 )
b1 7
11
#208000
01
#208500
b111 #
b111 <
b10 )
b10 7
11
#209000
01
#209500
b1000 #
b1000 <
b11 )
b11 7
11
#210000
01
#210500
b0 8
b1001 #
b1001 <
b100 )
b100 7
11
#211000
01
#211500
1+
b0 ,
b0 6
0*
1-
b1010 #
b1010 <
b0 )
b0 7
b0 :
11
#212000
01
#212500
b1011 #
b1011 <
b1 )
b1 7
11
#213000
01
#213500
b1100 #
b1100 <
b10 )
b10 7
11
#214000
01
#214500
b1101 #
b1101 <
b11 )
b11 7
11
#215000
01
#215500
b1110 #
b1110 <
b100 )
b100 7
11
#216000
01
#216500
b1111 #
b1111 <
b101 )
b101 7
11
#217000
01
#217500
b10000 #
b10000 <
b110 )
b110 7
11
#218000
01
#218500
b10001 #
b10001 <
b111 )
b111 7
11
#219000
01
#219500
b10010 #
b10010 <
b1000 )
b1000 7
11
#220000
01
#220500
b10011 #
b10011 <
b1001 )
b1001 7
11
#221000
01
#221500
b10100 #
b10100 <
b1010 )
b1010 7
11
#222000
01
#222500
b10101 #
b10101 <
b1011 )
b1011 7
11
#223000
01
#223500
b10110 #
b10110 <
b1100 )
b1100 7
11
#224000
01
#224500
b10111 #
b10111 <
b1101 )
b1101 7
11
#225000
01
#225500
b11000 #
b11000 <
b1110 )
b1110 7
11
